{
  "type": "minecraft:crafting_shapeless",
  "category": "misc",
  "ingredients": [
    {
      "item": "gemstonepower:electrum_tiny_pile"
    },
    {
      "item": "gemstonepower:electrum_tiny_pile"
    },
    {
      "item": "gemstonepower:electrum_tiny_pile"
    },
    {
      "item": "gemstonepower:electrum_tiny_pile"
    },
    {
      "item": "gemstonepower:electrum_tiny_pile"
    },
    {
      "item": "gemstonepower:electrum_tiny_pile"
    },
    {
      "item": "gemstonepower:electrum_tiny_pile"
    },
    {
      "item": "gemstonepower:electrum_tiny_pile"
    },
    {
      "item": "gemstonepower:electrum_tiny_pile"
    }
  ],
  "result": {
    "item": "gemstonepower:electrum_dust"
  }
}