{
  "type": "minecraft:crafting_shapeless",
  "category": "misc",
  "ingredients": [
    {
      "item": "gemstonepower:nickel_tiny_pile"
    },
    {
      "item": "gemstonepower:nickel_tiny_pile"
    },
    {
      "item": "gemstonepower:nickel_tiny_pile"
    },
    {
      "item": "gemstonepower:nickel_tiny_pile"
    },
    {
      "item": "gemstonepower:nickel_tiny_pile"
    },
    {
      "item": "gemstonepower:nickel_tiny_pile"
    },
    {
      "item": "gemstonepower:nickel_tiny_pile"
    },
    {
      "item": "gemstonepower:nickel_tiny_pile"
    },
    {
      "item": "gemstonepower:nickel_tiny_pile"
    }
  ],
  "result": {
    "item": "gemstonepower:nickel_dust"
  }
}