{
  "parent": "minecraft:recipes/root",
  "criteria": {
    "has_the_recipe": {
      "conditions": {
        "recipe": "minecraft:stick_from_wooden_door"
      },
      "trigger": "minecraft:recipe_unlocked"
    },
    "has_wooden_door": {
      "conditions": {
        "items": [
          {
            "tag": "minecraft:wooden_doors"
          }
        ]
      },
      "trigger": "minecraft:inventory_changed"
    }
  },
  "requirements": [
    [
      "has_the_recipe",
      "has_wooden_door"
    ]
  ],
  "rewards": {
    "recipes": [
      "minecraft:stick_from_wooden_door"
    ]
  },
  "sends_telemetry_event": false
}