{
  "parent": "minecraft:recipes/root",
  "criteria": {
    "has_beryllium_seed": {
      "conditions": {
        "items": [
          {
            "items": [
              "gemstonepower:beryllium_seed"
            ]
          }
        ]
      },
      "trigger": "minecraft:inventory_changed"
    },
    "has_the_recipe": {
      "conditions": {
        "recipe": "gemstonepower:beryllium_from_beryllium_seed"
      },
      "trigger": "minecraft:recipe_unlocked"
    }
  },
  "requirements": [
    [
      "has_beryllium_seed",
      "has_the_recipe"
    ]
  ],
  "rewards": {
    "recipes": [
      "gemstonepower:beryllium_from_beryllium_seed"
    ]
  },
  "sends_telemetry_event": true
}