{
  "parent": "minecraft:recipes/root",
  "criteria": {
    "has_bronze_ingot": {
      "conditions": {
        "items": [
          {
            "items": [
              "gemstonepower:bronze_ingot"
            ]
          }
        ]
      },
      "trigger": "minecraft:inventory_changed"
    },
    "has_the_recipe": {
      "conditions": {
        "recipe": "gemstonepower:bronze_dust_from_bronze_ingot"
      },
      "trigger": "minecraft:recipe_unlocked"
    }
  },
  "requirements": [
    [
      "has_the_recipe",
      "has_bronze_ingot"
    ]
  ],
  "rewards": {
    "recipes": [
      "gemstonepower:bronze_dust_from_bronze_ingot"
    ]
  },
  "sends_telemetry_event": false
}