{
  "parent": "minecraft:recipes/root",
  "criteria": {
    "has_peridot_charged": {
      "conditions": {
        "items": [
          {
            "items": [
              "gemstonepower:peridot_charged"
            ]
          }
        ]
      },
      "trigger": "minecraft:inventory_changed"
    },
    "has_the_recipe": {
      "conditions": {
        "recipe": "gemstonepower:peridot"
      },
      "trigger": "minecraft:recipe_unlocked"
    }
  },
  "requirements": [
    [
      "has_the_recipe",
      "has_peridot_charged"
    ]
  ],
  "rewards": {
    "recipes": [
      "gemstonepower:peridot"
    ]
  },
  "sends_telemetry_event": false
}